keble_exceptions/__init__.py
keble_exceptions/exceptions/__init__.py
keble_exceptions/exceptions/auth.py
keble_exceptions/exceptions/base.py
keble_exceptions/exceptions/data.py
keble_exceptions/exceptions/external_resource.py
keble_exceptions/exceptions/llm.py
keble_exceptions/exceptions/permission.py
keble_exceptions/exceptions/quota_limit.py
keble_exceptions/exceptions/utils.py
keble_exceptions/helpers.py
keble_exceptions-0.0.15.dist-info/METADATA
keble_exceptions-0.0.15.dist-info/WHEEL
keble_exceptions-0.0.15.dist-info/RECORD
