Metadata-Version: 2.1
Name: keble-exceptions
Version: 0.0.15
Summary: 
Author: zhenhao-ma
Author-email: bob0103779@gmail.com
Requires-Python: >=3.10,<4.0
Classifier: Programming Language :: Python :: 3
Classifier: Programming Language :: Python :: 3.10
Classifier: Programming Language :: Python :: 3.11
Classifier: Programming Language :: Python :: 3.12
Requires-Dist: sentry-sdk (>=2,<3)
